seq_aligner-0.1.5.dist-info/METADATA
seq_aligner-0.1.5.dist-info/WHEEL
seq_aligner/__init__.py
seq_aligner/seq_aligner.cpython-38-x86_64-linux-gnu.so
seq_aligner-0.1.5.dist-info/RECORD
